{"moduleName":null,"summaries":[{"symbol":{"__symbol":0,"members":[]},"metadata":{"__symbolic":"class","members":{"layoutNode":[{"__symbolic":"property","decorators":[{"__symbolic":"call","expression":{"__symbol":1,"members":[]}}]}],"layoutIndex":[{"__symbolic":"property","decorators":[{"__symbolic":"call","expression":{"__symbol":1,"members":[]}}]}],"dataIndex":[{"__symbolic":"property","decorators":[{"__symbolic":"call","expression":{"__symbol":1,"members":[]}}]}]}},"type":{"summaryKind":1,"type":{"reference":{"__symbol":0,"members":[]},"diDeps":[],"lifecycleHooks":[]},"isComponent":true,"selector":"none-widget","exportAs":null,"inputs":{"layoutNode":"layoutNode","layoutIndex":"layoutIndex","dataIndex":"dataIndex"},"outputs":{},"hostListeners":{},"hostProperties":{},"hostAttributes":{},"providers":[],"viewProviders":[],"queries":[],"guards":{},"viewQueries":[],"entryComponents":[],"changeDetection":1,"template":{"ngContentSelectors":[],"encapsulation":2},"componentViewType":{"__symbol":2,"members":[]},"rendererType":{"__symbol":3,"members":[]},"componentFactory":{"__symbol":4,"members":[]}}}],"symbols":[{"__symbol":0,"name":"NoneComponent","filePath":"./none.component"},{"__symbol":1,"name":"Input","filePath":"@angular/core"},{"__symbol":2,"name":"View_NoneComponent_0","filePath":"./none.component.ngfactory"},{"__symbol":3,"name":"RenderType_NoneComponent","filePath":"./none.component.ngfactory"},{"__symbol":4,"name":"NoneComponentNgFactory","filePath":"./none.component.ngfactory"}]}